{"nodes":[{"id":"main","label":"main.js","file_type":"code","source_file":"D:\\Kailash\\st-patricks\\src\\scripts\\main.js","source_location":"L1"},{"id":"main_animatemenutext","label":"animateMenuText()","file_type":"code","source_file":"D:\\Kailash\\st-patricks\\src\\scripts\\main.js","source_location":"L17"},{"id":"main_ismobile","label":"isMobile()","file_type":"code","source_file":"D:\\Kailash\\st-patricks\\src\\scripts\\main.js","source_location":"L43"},{"id":"main_getmenudirection","label":"getMenuDirection()","file_type":"code","source_file":"D:\\Kailash\\st-patricks\\src\\scripts\\main.js","source_location":"L58"},{"id":"main_setmenuimage","label":"setMenuImage()","file_type":"code","source_file":"D:\\Kailash\\st-patricks\\src\\scripts\\main.js","source_location":"L66"},{"id":"main_setactivesubgroup","label":"setActiveSubGroup()","file_type":"code","source_file":"D:\\Kailash\\st-patricks\\src\\scripts\\main.js","source_location":"L111"},{"id":"main_updatemenuforkey","label":"updateMenuForKey()","file_type":"code","source_file":"D:\\Kailash\\st-patricks\\src\\scripts\\main.js","source_location":"L193"},{"id":"main_getexpandedrightblockmaxwidth","label":"getExpandedRightBlockMaxWidth()","file_type":"code","source_file":"D:\\Kailash\\st-patricks\\src\\scripts\\main.js","source_location":"L233"},{"id":"main_revealbooktourbutton","label":"revealBookTourButton()","file_type":"code","source_file":"D:\\Kailash\\st-patricks\\src\\scripts\\main.js","source_location":"L240"},{"id":"main_setsearchoverlayvisibility","label":"setSearchOverlayVisibility()","file_type":"code","source_file":"D:\\Kailash\\st-patricks\\src\\scripts\\main.js","source_location":"L260"},{"id":"main_openmenu","label":"openMenu()","file_type":"code","source_file":"D:\\Kailash\\st-patricks\\src\\scripts\\main.js","source_location":"L289"},{"id":"main_closemenu","label":"closeMenu()","file_type":"code","source_file":"D:\\Kailash\\st-patricks\\src\\scripts\\main.js","source_location":"L464"},{"id":"main_initmobilemenu","label":"initMobileMenu()","file_type":"code","source_file":"D:\\Kailash\\st-patricks\\src\\scripts\\main.js","source_location":"L647"},{"id":"main_setactivemenuitem","label":"setActiveMenuItem()","file_type":"code","source_file":"D:\\Kailash\\st-patricks\\src\\scripts\\main.js","source_location":"L720"},{"id":"main_updateheaderonscroll","label":"updateHeaderOnScroll()","file_type":"code","source_file":"D:\\Kailash\\st-patricks\\src\\scripts\\main.js","source_location":"L751"},{"id":"main_initheroanimations","label":"initHeroAnimations()","file_type":"code","source_file":"D:\\Kailash\\st-patricks\\src\\scripts\\main.js","source_location":"L793"},{"id":"main_runpostloader","label":"runPostLoader()","file_type":"code","source_file":"D:\\Kailash\\st-patricks\\src\\scripts\\main.js","source_location":"L1082"},{"id":"main_initdropdownanimations","label":"initDropdownAnimations()","file_type":"code","source_file":"D:\\Kailash\\st-patricks\\src\\scripts\\main.js","source_location":"L1098"},{"id":"main_initheaderanimations","label":"initHeaderAnimations()","file_type":"code","source_file":"D:\\Kailash\\st-patricks\\src\\scripts\\main.js","source_location":"L1173"},{"id":"main_initnewsdetailheronavigationreveal","label":"initNewsDetailHeroNavigationReveal()","file_type":"code","source_file":"D:\\Kailash\\st-patricks\\src\\scripts\\main.js","source_location":"L1256"},{"id":"main_initgradientcirclefades","label":"initGradientCircleFades()","file_type":"code","source_file":"D:\\Kailash\\st-patricks\\src\\scripts\\main.js","source_location":"L1285"},{"id":"main_initfootergradientfade","label":"initFooterGradientFade()","file_type":"code","source_file":"D:\\Kailash\\st-patricks\\src\\scripts\\main.js","source_location":"L1308"},{"id":"main_initsectiongradientfades","label":"initSectionGradientFades()","file_type":"code","source_file":"D:\\Kailash\\st-patricks\\src\\scripts\\main.js","source_location":"L1333"},{"id":"main_wrapwords","label":"wrapWords()","file_type":"code","source_file":"D:\\Kailash\\st-patricks\\src\\scripts\\main.js","source_location":"L1361"},{"id":"main_wrapsentences","label":"wrapSentences()","file_type":"code","source_file":"D:\\Kailash\\st-patricks\\src\\scripts\\main.js","source_location":"L1390"},{"id":"main_initaboutreveal","label":"initAboutReveal()","file_type":"code","source_file":"D:\\Kailash\\st-patricks\\src\\scripts\\main.js","source_location":"L1402"},{"id":"main_initlatestnewsslider","label":"initLatestNewsSlider()","file_type":"code","source_file":"D:\\Kailash\\st-patricks\\src\\scripts\\main.js","source_location":"L1460"},{"id":"main_initstatsanimation","label":"initStatsAnimation()","file_type":"code","source_file":"D:\\Kailash\\st-patricks\\src\\scripts\\main.js","source_location":"L1564"},{"id":"main_initcontactcardsanimation","label":"initContactCardsAnimation()","file_type":"code","source_file":"D:\\Kailash\\st-patricks\\src\\scripts\\main.js","source_location":"L1727"},{"id":"main_initcontactformdropdowns","label":"initContactFormDropdowns()","file_type":"code","source_file":"D:\\Kailash\\st-patricks\\src\\scripts\\main.js","source_location":"L1814"},{"id":"main_initslides","label":"initSlides()","file_type":"code","source_file":"D:\\Kailash\\st-patricks\\src\\scripts\\main.js","source_location":"L1961"},{"id":"main_gotoslide","label":"goToSlide()","file_type":"code","source_file":"D:\\Kailash\\st-patricks\\src\\scripts\\main.js","source_location":"L2002"},{"id":"main_updatenavstate","label":"updateNavState()","file_type":"code","source_file":"D:\\Kailash\\st-patricks\\src\\scripts\\main.js","source_location":"L2116"},{"id":"main_nextslide","label":"nextSlide()","file_type":"code","source_file":"D:\\Kailash\\st-patricks\\src\\scripts\\main.js","source_location":"L2126"},{"id":"main_prevslide","label":"prevSlide()","file_type":"code","source_file":"D:\\Kailash\\st-patricks\\src\\scripts\\main.js","source_location":"L2131"},{"id":"main_startvideoplayback","label":"startVideoPlayback()","file_type":"code","source_file":"D:\\Kailash\\st-patricks\\src\\scripts\\main.js","source_location":"L2175"},{"id":"main_initfootermarquee","label":"initFooterMarquee()","file_type":"code","source_file":"D:\\Kailash\\st-patricks\\src\\scripts\\main.js","source_location":"L2210"},{"id":"main_initgradientcursoreffect","label":"initGradientCursorEffect()","file_type":"code","source_file":"D:\\Kailash\\st-patricks\\src\\scripts\\main.js","source_location":"L2365"},{"id":"main_initfootergradientcursoreffect","label":"initFooterGradientCursorEffect()","file_type":"code","source_file":"D:\\Kailash\\st-patricks\\src\\scripts\\main.js","source_location":"L2455"},{"id":"main_inittestimonialsgradientcursoreffect","label":"initTestimonialsGradientCursorEffect()","file_type":"code","source_file":"D:\\Kailash\\st-patricks\\src\\scripts\\main.js","source_location":"L2551"},{"id":"main_initlatestnewsheroslider","label":"initLatestNewsHeroSlider()","file_type":"code","source_file":"D:\\Kailash\\st-patricks\\src\\scripts\\main.js","source_location":"L2643"},{"id":"main_initcocurricularslider","label":"initCocurricularSlider()","file_type":"code","source_file":"D:\\Kailash\\st-patricks\\src\\scripts\\main.js","source_location":"L2825"},{"id":"main_livesearch","label":"liveSearch()","file_type":"code","source_file":"D:\\Kailash\\st-patricks\\src\\scripts\\main.js","source_location":"L3003"},{"id":"main_initsearch","label":"initSearch()","file_type":"code","source_file":"D:\\Kailash\\st-patricks\\src\\scripts\\main.js","source_location":"L3028"}],"edges":[{"source":"main","target":"main_animatemenutext","relation":"contains","confidence":"EXTRACTED","source_file":"D:\\Kailash\\st-patricks\\src\\scripts\\main.js","source_location":"L17","weight":1},{"source":"main","target":"main_ismobile","relation":"contains","confidence":"EXTRACTED","source_file":"D:\\Kailash\\st-patricks\\src\\scripts\\main.js","source_location":"L43","weight":1},{"source":"main","target":"main_getmenudirection","relation":"contains","confidence":"EXTRACTED","source_file":"D:\\Kailash\\st-patricks\\src\\scripts\\main.js","source_location":"L58","weight":1},{"source":"main","target":"main_setmenuimage","relation":"contains","confidence":"EXTRACTED","source_file":"D:\\Kailash\\st-patricks\\src\\scripts\\main.js","source_location":"L66","weight":1},{"source":"main","target":"main_setactivesubgroup","relation":"contains","confidence":"EXTRACTED","source_file":"D:\\Kailash\\st-patricks\\src\\scripts\\main.js","source_location":"L111","weight":1},{"source":"main","target":"main_updatemenuforkey","relation":"contains","confidence":"EXTRACTED","source_file":"D:\\Kailash\\st-patricks\\src\\scripts\\main.js","source_location":"L193","weight":1},{"source":"main","target":"main_getexpandedrightblockmaxwidth","relation":"contains","confidence":"EXTRACTED","source_file":"D:\\Kailash\\st-patricks\\src\\scripts\\main.js","source_location":"L233","weight":1},{"source":"main","target":"main_revealbooktourbutton","relation":"contains","confidence":"EXTRACTED","source_file":"D:\\Kailash\\st-patricks\\src\\scripts\\main.js","source_location":"L240","weight":1},{"source":"main","target":"main_setsearchoverlayvisibility","relation":"contains","confidence":"EXTRACTED","source_file":"D:\\Kailash\\st-patricks\\src\\scripts\\main.js","source_location":"L260","weight":1},{"source":"main","target":"main_openmenu","relation":"contains","confidence":"EXTRACTED","source_file":"D:\\Kailash\\st-patricks\\src\\scripts\\main.js","source_location":"L289","weight":1},{"source":"main","target":"main_closemenu","relation":"contains","confidence":"EXTRACTED","source_file":"D:\\Kailash\\st-patricks\\src\\scripts\\main.js","source_location":"L464","weight":1},{"source":"main","target":"main_initmobilemenu","relation":"contains","confidence":"EXTRACTED","source_file":"D:\\Kailash\\st-patricks\\src\\scripts\\main.js","source_location":"L647","weight":1},{"source":"main","target":"main_setactivemenuitem","relation":"contains","confidence":"EXTRACTED","source_file":"D:\\Kailash\\st-patricks\\src\\scripts\\main.js","source_location":"L720","weight":1},{"source":"main","target":"main_updateheaderonscroll","relation":"contains","confidence":"EXTRACTED","source_file":"D:\\Kailash\\st-patricks\\src\\scripts\\main.js","source_location":"L751","weight":1},{"source":"main","target":"main_initheroanimations","relation":"contains","confidence":"EXTRACTED","source_file":"D:\\Kailash\\st-patricks\\src\\scripts\\main.js","source_location":"L793","weight":1},{"source":"main","target":"main_runpostloader","relation":"contains","confidence":"EXTRACTED","source_file":"D:\\Kailash\\st-patricks\\src\\scripts\\main.js","source_location":"L1082","weight":1},{"source":"main","target":"main_initdropdownanimations","relation":"contains","confidence":"EXTRACTED","source_file":"D:\\Kailash\\st-patricks\\src\\scripts\\main.js","source_location":"L1098","weight":1},{"source":"main","target":"main_initheaderanimations","relation":"contains","confidence":"EXTRACTED","source_file":"D:\\Kailash\\st-patricks\\src\\scripts\\main.js","source_location":"L1173","weight":1},{"source":"main","target":"main_initnewsdetailheronavigationreveal","relation":"contains","confidence":"EXTRACTED","source_file":"D:\\Kailash\\st-patricks\\src\\scripts\\main.js","source_location":"L1256","weight":1},{"source":"main","target":"main_initgradientcirclefades","relation":"contains","confidence":"EXTRACTED","source_file":"D:\\Kailash\\st-patricks\\src\\scripts\\main.js","source_location":"L1285","weight":1},{"source":"main","target":"main_initfootergradientfade","relation":"contains","confidence":"EXTRACTED","source_file":"D:\\Kailash\\st-patricks\\src\\scripts\\main.js","source_location":"L1308","weight":1},{"source":"main","target":"main_initsectiongradientfades","relation":"contains","confidence":"EXTRACTED","source_file":"D:\\Kailash\\st-patricks\\src\\scripts\\main.js","source_location":"L1333","weight":1},{"source":"main","target":"main_wrapwords","relation":"contains","confidence":"EXTRACTED","source_file":"D:\\Kailash\\st-patricks\\src\\scripts\\main.js","source_location":"L1361","weight":1},{"source":"main","target":"main_wrapsentences","relation":"contains","confidence":"EXTRACTED","source_file":"D:\\Kailash\\st-patricks\\src\\scripts\\main.js","source_location":"L1390","weight":1},{"source":"main","target":"main_initaboutreveal","relation":"contains","confidence":"EXTRACTED","source_file":"D:\\Kailash\\st-patricks\\src\\scripts\\main.js","source_location":"L1402","weight":1},{"source":"main","target":"main_initlatestnewsslider","relation":"contains","confidence":"EXTRACTED","source_file":"D:\\Kailash\\st-patricks\\src\\scripts\\main.js","source_location":"L1460","weight":1},{"source":"main","target":"main_initstatsanimation","relation":"contains","confidence":"EXTRACTED","source_file":"D:\\Kailash\\st-patricks\\src\\scripts\\main.js","source_location":"L1564","weight":1},{"source":"main","target":"main_initcontactcardsanimation","relation":"contains","confidence":"EXTRACTED","source_file":"D:\\Kailash\\st-patricks\\src\\scripts\\main.js","source_location":"L1727","weight":1},{"source":"main","target":"main_initcontactformdropdowns","relation":"contains","confidence":"EXTRACTED","source_file":"D:\\Kailash\\st-patricks\\src\\scripts\\main.js","source_location":"L1814","weight":1},{"source":"main","target":"main_initslides","relation":"contains","confidence":"EXTRACTED","source_file":"D:\\Kailash\\st-patricks\\src\\scripts\\main.js","source_location":"L1961","weight":1},{"source":"main","target":"main_gotoslide","relation":"contains","confidence":"EXTRACTED","source_file":"D:\\Kailash\\st-patricks\\src\\scripts\\main.js","source_location":"L2002","weight":1},{"source":"main","target":"main_updatenavstate","relation":"contains","confidence":"EXTRACTED","source_file":"D:\\Kailash\\st-patricks\\src\\scripts\\main.js","source_location":"L2116","weight":1},{"source":"main","target":"main_nextslide","relation":"contains","confidence":"EXTRACTED","source_file":"D:\\Kailash\\st-patricks\\src\\scripts\\main.js","source_location":"L2126","weight":1},{"source":"main","target":"main_prevslide","relation":"contains","confidence":"EXTRACTED","source_file":"D:\\Kailash\\st-patricks\\src\\scripts\\main.js","source_location":"L2131","weight":1},{"source":"main","target":"main_startvideoplayback","relation":"contains","confidence":"EXTRACTED","source_file":"D:\\Kailash\\st-patricks\\src\\scripts\\main.js","source_location":"L2175","weight":1},{"source":"main","target":"main_initfootermarquee","relation":"contains","confidence":"EXTRACTED","source_file":"D:\\Kailash\\st-patricks\\src\\scripts\\main.js","source_location":"L2210","weight":1},{"source":"main","target":"main_initgradientcursoreffect","relation":"contains","confidence":"EXTRACTED","source_file":"D:\\Kailash\\st-patricks\\src\\scripts\\main.js","source_location":"L2365","weight":1},{"source":"main","target":"main_initfootergradientcursoreffect","relation":"contains","confidence":"EXTRACTED","source_file":"D:\\Kailash\\st-patricks\\src\\scripts\\main.js","source_location":"L2455","weight":1},{"source":"main","target":"main_inittestimonialsgradientcursoreffect","relation":"contains","confidence":"EXTRACTED","source_file":"D:\\Kailash\\st-patricks\\src\\scripts\\main.js","source_location":"L2551","weight":1},{"source":"main","target":"main_initlatestnewsheroslider","relation":"contains","confidence":"EXTRACTED","source_file":"D:\\Kailash\\st-patricks\\src\\scripts\\main.js","source_location":"L2643","weight":1},{"source":"main","target":"main_initcocurricularslider","relation":"contains","confidence":"EXTRACTED","source_file":"D:\\Kailash\\st-patricks\\src\\scripts\\main.js","source_location":"L2825","weight":1},{"source":"main","target":"main_livesearch","relation":"contains","confidence":"EXTRACTED","source_file":"D:\\Kailash\\st-patricks\\src\\scripts\\main.js","source_location":"L3003","weight":1},{"source":"main","target":"main_initsearch","relation":"contains","confidence":"EXTRACTED","source_file":"D:\\Kailash\\st-patricks\\src\\scripts\\main.js","source_location":"L3028","weight":1},{"source":"main_updatemenuforkey","target":"main_getmenudirection","relation":"calls","confidence":"EXTRACTED","source_file":"D:\\Kailash\\st-patricks\\src\\scripts\\main.js","source_location":"L197","weight":1},{"source":"main_updatemenuforkey","target":"main_setactivesubgroup","relation":"calls","confidence":"EXTRACTED","source_file":"D:\\Kailash\\st-patricks\\src\\scripts\\main.js","source_location":"L206","weight":1},{"source":"main_updatemenuforkey","target":"main_setmenuimage","relation":"calls","confidence":"EXTRACTED","source_file":"D:\\Kailash\\st-patricks\\src\\scripts\\main.js","source_location":"L210","weight":1},{"source":"main_openmenu","target":"main_animatemenutext","relation":"calls","confidence":"EXTRACTED","source_file":"D:\\Kailash\\st-patricks\\src\\scripts\\main.js","source_location":"L325","weight":1},{"source":"main_openmenu","target":"main_setsearchoverlayvisibility","relation":"calls","confidence":"EXTRACTED","source_file":"D:\\Kailash\\st-patricks\\src\\scripts\\main.js","source_location":"L331","weight":1},{"source":"main_openmenu","target":"main_setactivemenuitem","relation":"calls","confidence":"EXTRACTED","source_file":"D:\\Kailash\\st-patricks\\src\\scripts\\main.js","source_location":"L338","weight":1},{"source":"main_openmenu","target":"main_updatemenuforkey","relation":"calls","confidence":"EXTRACTED","source_file":"D:\\Kailash\\st-patricks\\src\\scripts\\main.js","source_location":"L343","weight":1},{"source":"main_openmenu","target":"main_ismobile","relation":"calls","confidence":"EXTRACTED","source_file":"D:\\Kailash\\st-patricks\\src\\scripts\\main.js","source_location":"L346","weight":1},{"source":"main_closemenu","target":"main_ismobile","relation":"calls","confidence":"EXTRACTED","source_file":"D:\\Kailash\\st-patricks\\src\\scripts\\main.js","source_location":"L617","weight":1},{"source":"main_initmobilemenu","target":"main_ismobile","relation":"calls","confidence":"EXTRACTED","source_file":"D:\\Kailash\\st-patricks\\src\\scripts\\main.js","source_location":"L648","weight":1},{"source":"main_runpostloader","target":"main_initheroanimations","relation":"calls","confidence":"EXTRACTED","source_file":"D:\\Kailash\\st-patricks\\src\\scripts\\main.js","source_location":"L1083","weight":1},{"source":"main_runpostloader","target":"main_initheaderanimations","relation":"calls","confidence":"EXTRACTED","source_file":"D:\\Kailash\\st-patricks\\src\\scripts\\main.js","source_location":"L1084","weight":1},{"source":"main_initfootergradientfade","target":"main_ismobile","relation":"calls","confidence":"EXTRACTED","source_file":"D:\\Kailash\\st-patricks\\src\\scripts\\main.js","source_location":"L1313","weight":1},{"source":"main_initaboutreveal","target":"main_wrapwords","relation":"calls","confidence":"EXTRACTED","source_file":"D:\\Kailash\\st-patricks\\src\\scripts\\main.js","source_location":"L1416","weight":1},{"source":"main_gotoslide","target":"main_updatenavstate","relation":"calls","confidence":"EXTRACTED","source_file":"D:\\Kailash\\st-patricks\\src\\scripts\\main.js","source_location":"L2008","weight":1},{"source":"main_nextslide","target":"main_gotoslide","relation":"calls","confidence":"EXTRACTED","source_file":"D:\\Kailash\\st-patricks\\src\\scripts\\main.js","source_location":"L2128","weight":1},{"source":"main_prevslide","target":"main_gotoslide","relation":"calls","confidence":"EXTRACTED","source_file":"D:\\Kailash\\st-patricks\\src\\scripts\\main.js","source_location":"L2133","weight":1},{"source":"main_initlatestnewsheroslider","target":"main_updatenavstate","relation":"calls","confidence":"EXTRACTED","source_file":"D:\\Kailash\\st-patricks\\src\\scripts\\main.js","source_location":"L2756","weight":1},{"source":"main_initsearch","target":"main_livesearch","relation":"calls","confidence":"EXTRACTED","source_file":"D:\\Kailash\\st-patricks\\src\\scripts\\main.js","source_location":"L3283","weight":1}]}